spothinta/__init__.py
spothinta/const.py
spothinta/exceptions.py
spothinta/models.py
spothinta/py.typed
spothinta/spothinta.py
spothinta-0.1.1.dist-info/LICENSE
spothinta-0.1.1.dist-info/METADATA
spothinta-0.1.1.dist-info/WHEEL
spothinta-0.1.1.dist-info/entry_points.txt
spothinta-0.1.1.dist-info/RECORD
