Metadata-Version: 2.1
Name: spothinta
Version: 0.1.1
Summary: Asynchronous Python client providing energy prices from spot-hinta.fi
License: MIT
Keywords: energy,spothinta,prices,api,async,client
Author: Sebastian Lövdahl
Author-email: sebastian.lovdahl@hibox.fi
Maintainer: Sebastian Lövdahl
Maintainer-email: sebastian.lovdahl@hibox.fi
Requires-Python: >=3.9,<4.0
Classifier: Framework :: AsyncIO
Classifier: Intended Audience :: Developers
Classifier: License :: OSI Approved :: MIT License
Classifier: Natural Language :: English
Classifier: Programming Language :: Python :: 3
Classifier: Programming Language :: Python :: 3.9
Classifier: Programming Language :: Python :: 3.10
Classifier: Programming Language :: Python :: 3.11
Classifier: Topic :: Software Development :: Libraries :: Python Modules
Requires-Dist: aiohttp (>=3.0.0)
Requires-Dist: yarl (>=1.6.0)
